conmongo
